[
    {
        "week":"1",
        "name": "HTML, CSS & GIT",
        "complete": true
    },
    {
        "week":"2",
        "name": "MORE CSS",
        "complete": true
    },
    {
        "week":"3",
        "name": "UX & BOOTSTRAP",
        "complete": true
    },
    {
        "week":"4",
        "name": "JS FUNDAMENTALS",
        "complete": true
    },
    {
        "week":"5",
        "name": "INTERMEDIATE JS",
        "complete": true
    },
    {
        "week":"6",
        "name": "WEB APIS",
        "complete": true
    },
    {
        "week":"7",
        "name": "3RD PARTY APIS",
        "complete": true
    },
    {
        "week":"8",
        "name": "SERVER APIS",
        "complete": true
    },
    {
        "week":"9",
        "name": "PROJECT 1",
        "complete": true
    },
    {
        "week":"10",
        "name": "ES6 & NODE.JS",
        "complete": true
    },
    {
        "week":"11",
        "name": "TEST DRIVEN DEVELOPMENT",
        "complete": true
    },
    {
        "week":"12",
        "name": "REACT",
        "complete": true
    },
    {
        "week":"13",
        "name": "ADVANCED REACT"
    },
    {
        "week":"14",
        "name": "FINAL PROJECT"
    },
    {
        "week":"15",
        "name": "FINAL PROJECT"
    },
    {
        "week":"16",
        "name": "FINAL PROJECT"
    }
]